Metadata-Version: 2.1
Name: PyTimbrRestAPI
Version: 1.0.0
Summary: Timbr REST API connector
Home-page: https://github.com/WPSemantix/timbr_python_http
Author: timbr
Author-email: contact@timbr.ai
License: MIT
Project-URL: Bug Tracker, https://github.com/WPSemantix/timbr_python_http/issues
Keywords: timbr,timbr-http,timbr-https,timbr-rest,timbr-api,timbr-rest-api,timbr-connector,PyTimbrRestAPI,PyTimbr
Platform: UNKNOWN
Classifier: Development Status :: 5 - Production/Stable
Classifier: Intended Audience :: Developers
Classifier: Topic :: Software Development :: Build Tools
Classifier: License :: OSI Approved :: MIT License
Classifier: Programming Language :: Python :: 3
Classifier: Programming Language :: Python :: 3.7
Classifier: Programming Language :: Python :: 3.8
Classifier: Programming Language :: Python :: 3.9
License-File: LICENSE
